cltrier_promptClassify/__init__.py
cltrier_promptClassify/__main__.py
cltrier_promptClassify/dataset.py
cltrier_promptClassify/util.py
cltrier_promptClassify/integrations/__init__.py
cltrier_promptClassify/integrations/base.py
cltrier_promptClassify/integrations/huggingface.py
cltrier_promptclassify-0.0.1.dist-info/LICENSE
cltrier_promptclassify-0.0.1.dist-info/WHEEL
cltrier_promptclassify-0.0.1.dist-info/METADATA
cltrier_promptclassify-0.0.1.dist-info/RECORD
