Metadata-Version: 2.1
Name: cltrier_promptClassify
Version: 0.0.1
Summary: Description needed
Author-email: Simon Münker <muenker@uni-trier.com>
Requires-Python: >=3.10
Classifier: Development Status :: 3 - Alpha
Classifier: Intended Audience :: Developers
Classifier: License :: OSI Approved :: MIT License
Classifier: Programming Language :: Python :: 3.10
Requires-Dist: tomli>=2.0.0
Requires-Dist: pyarrow>=13.0.0
Requires-Dist: tqdm>=4.66.0
Requires-Dist: numpy>=1.25.0
Requires-Dist: pandas>=2.1.0
Requires-Dist: torch>=2.0.0
Requires-Dist: transformers>=4.32.0
Requires-Dist: matplotlib>=3.7.0
Requires-Dist: seaborn>=0.12.0
Requires-Dist: scikit-learn>=1.2.0
